gdmloader/__init__.py
gdmloader/constants.py
gdmloader/source.py
gdmloader/version.py
gdmloader-0.0.3.dist-info/METADATA
gdmloader-0.0.3.dist-info/WHEEL
gdmloader-0.0.3.dist-info/RECORD
