Metadata-Version: 2.4
Name: gdmloader
Version: 0.0.3
Project-URL: Documentation, https://github.com/NREL-Distribution-Suites/gdmloader#readme
Project-URL: Issues, https://github.com/NREL-Distribution-Suites/gdmloader/issues
Project-URL: Source, https://github.com/NREL-Distribution-Suites/gdmloader
Author-email: Kapil Duwadi <Kapil.Duwadi@nrel.gov>, Aadil Latif <Aadil.Latif@nrel.gov>
License-Expression: BSD-3-Clause
Classifier: License :: OSI Approved :: BSD License
Classifier: Operating System :: OS Independent
Classifier: Programming Language :: Python :: 3.11
Requires-Python: >=3.11
Requires-Dist: fsspec~=2025.3.2
Requires-Dist: gcsfs~=2025.3.2
Requires-Dist: grid-data-models
Requires-Dist: requests~=2.32.3
Provides-Extra: dev
Requires-Dist: pre-commit; extra == 'dev'
Requires-Dist: pytest; extra == 'dev'
Requires-Dist: pytest-cov; extra == 'dev'
Requires-Dist: ruff; extra == 'dev'
